<?xml version="1.0" encoding="iso-8859-15"?>
<Collections>
      <Collection>
        <DealType>Account</DealType>
        <MsgID>9</MsgID>
        <ExecType>1</ExecType>
        <TradeDate>05/06/2018</TradeDate>
        <ExtRefNo>INVESTMENT/DEPOSIT</ExtRefNo>
        <ExternalCustomer>INV-OTH</ExternalCustomer>
        <Direction>DEPO</Direction>
        <Rate>0</Rate>
        <DealtCurrency>GBP</DealtCurrency>
        <DealtAmount>0</DealtAmount>
        <Book>INVESTMENT</Book>
        <ValueDate>02/01/2018</ValueDate>
        <MaturityDate></MaturityDate>
        <InterestFrequency>1M</InterestFrequency>
        <InterestRateType>Fixed</InterestRateType>
        <FloatingRateMargin></FloatingRateMargin>
        <InterestAction>0</InterestAction>
        <Notes>Investment [DEPOSIT][INVESTMENT][INV-OTH]</Notes>
        <AccountName>Investment [DEPOSIT]</AccountName>
        <AccountNumber>INVESTMENT/DEPOSIT</AccountNumber>
        <MandatedUser>Default INV</MandatedUser>
      </Collection>
</Collections>
