<?xml version="1.0" encoding="iso-8859-15"?>
<Collections>
      <Collection>
        <ParentExtRefNo>INCREDITCL/B-VETF</ParentExtRefNo>
        <DealType>Account Amendment</DealType>
        <ExecType>0</ExecType>
        <ValueDate>07/06/2018</ValueDate>
        <Adjustment>79.43</Adjustment>
        <Notes>In Credit Clearing/B-vetf/18-01-10/17:00 (prev)</Notes>
        <InterestRateType>Fixed</InterestRateType>
        <ExtRefNo>0180524170000711</ExtRefNo>
        <RedefaultValues>N</RedefaultValues>
        <Portfolio>0</Portfolio>
        <Book>INCREDITCL</Book>
      </Collection>
</Collections>
