<?xml version="1.0" encoding="iso-8859-15"?>
<Collections>
      <Collection>
        <ParentExtRefNo>INDEBITCLE/B-VMTF</ParentExtRefNo>
        <DealType>Account Amendment</DealType>
        <ExecType>0</ExecType>
        <ValueDate>31/08/2018</ValueDate>
        <Adjustment>9451.95</Adjustment>
        <Notes>In Debit Clearing/B-vmtf/15-04-10/17:00 (prev)</Notes>
        <InterestRateType>Fixed</InterestRateType>
        <ExtRefNo>0180524170000785</ExtRefNo>
        <RedefaultValues>N</RedefaultValues>
        <Portfolio>0</Portfolio>
        <Book>INDEBITCLE</Book>
      </Collection>
</Collections>
