<?xml version="1.0" encoding="iso-8859-15"?>
<Collections>
      <Collection>
        <ParentExtRefNo>INVESTMENT/DEPOSIT</ParentExtRefNo>
        <DealType>Account Amendment</DealType>
        <ExecType>1</ExecType>
        <ValueDate>02/10/2018</ValueDate>
        <Adjustment>2065.13</Adjustment>
        <Notes>Investment/DEPOSIT/02-10-18/09:30</Notes>
        <InterestRateType>Fixed</InterestRateType>
        <ExtRefNo>1180604093001746</ExtRefNo>
        <RedefaultValues>N</RedefaultValues>
        <Portfolio>CF-01</Portfolio>
        <Book>INVESTMENT</Book>
      </Collection>
</Collections>
