<?xml version="1.0" encoding="iso-8859-15"?>
<Collections>
      <Collection>
        <ParentExtRefNo>BRL.CUSTINSTA.BDB111</ParentExtRefNo>
        <DealType>Customer Payment Instruction</DealType>
        <MsgID>d5306329-67aa-16e0-1306-d112dcca1d72-098</MsgID>
        <ExecType>0</ExecType>
        <TradeDate>12/11/19</TradeDate>
        <ExtRefNo>six-u1-1300-2e9c6-0098</ExtRefNo>
        <ExternalCustomer>BDB</ExternalCustomer>
        <PaymentSyste,>SWIFT</PaymentSyste,>
        <Direction>PAY</Direction>
        <DealtCurrency>BRL</DealtCurrency>
        <Adjustment>-9220.4</Adjustment>
        <Book>CUSTINST-A</Book>
        <InterestRate>Fixed</InterestRate>
        <Notes>[UC1]Customer Payment Instruction [13:00]</Notes>
        <MandatedUser>DEFAULT</MandatedUser>
        <LEI>BDBD530632967AA16E01</LEI>
        <RedefaultValues>N</RedefaultValues>
        <Portfolio>ACTUAL</Portfolio>
      </Collection>
</Collections>
